{  
   "heading":"122",
   "activity":[  
      {  
         "extra":[  
            {  
               "intVal":null,
               "name":null,
               "type":null
            }
         ],
         "activity":[  
            {  
               "confidence":"75",
               "type":"IN_VEHICLE"
            },
            {  
               "confidence":"10",
               "type":"ON_FOOT"
            },
            {  
               "confidence":"5",
               "type":"ON_BICYCLE"
            },
            {  
               "confidence":"5",
               "type":"STILL"
            },
            {  
               "confidence":"5",
               "type":"UNKNOWN"
            },
            {  
               "confidence":"5",
               "type":"WALKING"
            },
            {  
               "confidence":"5",
               "type":"RUNNING"
            }
         ],
         "timestampMs":"1486800273394"
      }
   ],
   "verticalAccuracy":null,
   "velocity":"35",
   "accuracy":"34",
   "longitudeE7":"116593258",
   "latitudeE7":"481265044",
   "altitude":"519",
   "timestampMs":"1486800415000"
}
